{
  "postId": 99,
  "url": "https://www.capitalgroup.com/advisor/insights/articles/why-next-economic-recovery-may-be-stronger-than-expected.html",
  "source": "wayback",
  "fetched_at": "2026-05-18T20:33:23Z",
  "fetch_status": "ok",
  "http_status": 200,
  "title": "Why the next economic recovery may be stronger than expected",
  "body": "Three questions have weighed on investors\u2019 minds for months: Will there be a recession? How bad will it be? And what comes next?\nThe U.S. Federal Reserve\u2019s aggressive campaign of interest rate hikes to combat persistent inflation has amplified the risk of recession. Recent banking sector turmoil, which will likely result in tighter credit conditions, could further that risk.\n\u201cOne reliable indicator of a recession is an inverted yield curve, where the yield on short-term U.S. Treasury bonds is higher than the yield on longer dated bonds,\u201c says U.S. economist Jared Franz. \u201cRecent activity in bond markets suggests a recession is widely expected. In fact, this may be the most widely anticipated recession in decades.\u201d\nThe inverted yield curve warns of recession risk\nWhile many investors are focused on the timing and severity of the next recession, Franz has turned his focus to longer term questions: What could be the catalysts for a subsequent recovery? And what are some of the implications of that recovery for investor portfolios?\n\u201cWhen an insight is widely held, it can be challenging to benefit from that insight, as it may already be priced into the market,\u201d Franz says. \u201cInstead, investors may be better served by preparing for what I believe will be a stronger than usual recovery, fueled by a healthy consumer sector.\u201d\nHere, Franz shares his expectations for recession and his perspective on a potential subsequent recovery.\nWatch it on demand\nCE credit available\nI believe we are on the edge of a recession. And with inflation still above the Fed\u2019s 2% target and labor markets tight, the central bank still has work to do. Given the recent banking upheaval, I believe the Fed may temper its approach to rate increases, but I do believe it will be prepared to hike rates until inflation slows further.\nI now expect a 1.0% decline in gross domestic product (GDP), or what would be considered a \u201cmild\u201d recession. That would be considerably milder than the 4.5% decline investors experienced during the global financial crisis (GFC) from 2007 to 2009, and closer to a more conventional recession. This is not to diminish the impact of recession on individuals. Recessions, no matter how mild, can be painful.\nA weakening housing market is another risk factor. Sales fell in March, resulting in home price declines for a second straight month. But from here, I expect that prices may have a further 10% downside followed by a reacceleration. This will help limit any deterioration in household balance sheets, which may provide a boost to consumer confidence.\nIf there is one, I believe there are two reasons a recovery will be stronger than prior cycles. First, there may not be a need for large-scale deleveraging like there was during the GFC. Because so many companies have been expecting economic weakness, businesses have taken action, delaying orders to work excesses out of the economy. So, while a recession is likely this year, I expect it will be somewhat shallow.\nSecond, the U.S. consumer sector is strong relative to past cycles. Healthy job markets, wage growth and household wealth should be key catalysts for a more robust recovery.\nCertainly, the U.S. labor market has been softening recently, and a recession of any magnitude will likely drive unemployment higher as companies announce layoffs. But the labor market has shown continued strength, with 236,000 jobs added in March. Why is that? Structural changes in labor markets have shifted labor supply and demand dynamics.\nAt the end of March, the unemployment rate stood at 3.5%, near multidecade lows. As the economy slows, unemployment will rise from here, but I believe it will peak around 5.0% and fall more quickly than we have seen in prior business cycles. And, since the start of the pandemic, work-from-home trends, along with the reshoring of supply chains back to the U.S. and the development of sustainable energy, have bolstered real wages, particularly for middle- and low-income workers.\nWhat\u2019s more, at this point in the cycle, consumers have low debt relative to levels coming out of the GFC or even other more typical recessions. At the end of 2022, household debt service as a percentage of income stood at 9.7%.\nConsumers are in better shape than they have been ahead of past recessions\nI expect moderating inflation to further support consumer strength. While it will take some time for the Fed to get inflation down to its 2.0% target, I believe it will be contained near 3.0%. Academic studies have shown that consumer spending has tended not to be significantly impacted by inflation around 3.0%. Contained inflation will likely boost consumer confidence. And, if wages hold up, it can feel like a real wage boost. I also expect inflation to edge toward 2.0% to 2.5% by 2025.\nI believe we\u2019ll also see productivity gains from automation and the increased adoption of artificial intelligence. This may provide an economic tailwind by helping to manage rising labor costs. That said, I do not expect such productivity gains to offset hiring needs in the near- to mid-term.\nI also expect we will see stronger housing demand coming out of the recession. Changing demographics and rising household formation (a group of individuals who intend to live together), suggest a likely rebound in housing demand. I expect the popularity of working remotely to drive demand for housing development in suburbs, areas beyond the suburbs and second-tier cities, as well.\nSolid labor market fundamentals, household balance sheets and moderating inflation could in my estimation lead to 3.0% growth in the U.S. consumer sector going forward. This is important because consumers account for about 67% of the U.S. economy. It is important to emphasize that a recession will cause some contraction in the labor market, but I expect the labor market to rebound.\nStrong wages and consumer confidence could boost consumer spending, providing an uptick in a range of industries, including travel and leisure. What\u2019s more, a housing market recovery could provide a tailwind not only to construction spending, but also spending for other durable goods, like household appliances.\nHistorically, the stock market has tended to anticipate recoveries, rebounding ahead of any turn in the economy.\nAfter large declines, markets have rebounded relatively quickly\nThe S&P 500 Index is a market capitalization-weighted index based on the results of approximately 500 widely held common stocks. The index is unmanaged and, therefore, has no expenses. Investors cannot invest directly in an index.\nThe S&P 500 Index is a product of S&P Dow Jones Indices LLC and/or its affiliates and has been licensed for use by Capital Group. Copyright \u00a9 2023 S&P Dow Jones Indices LLC, a division of S&P Global, and/or its affiliates. All rights reserved. Redistribution or reproduction in whole or in part are prohibited without written permission of S&P Dow Jones Indices LLC.\nDefined Contribution\nMarket Volatility\nRELATED INSIGHTS\nEconomic Indicators\nAsset Allocation\nThe Capital Ideas newsletter delivers weekly investment insights straight to your inbox.\nInvestments are not FDIC-insured, nor are they deposits of or guaranteed by a bank or any other entity, so they may lose value.\nInvestors should carefully consider investment objectives, risks, charges and expenses. This and other important information is contained in the fund prospectuses and summary prospectuses, which can be obtained from a financial professional and should be read carefully before investing.\nStatements attributed to an individual represent the opinions of that individual as of the date published and do not necessarily reflect the opinions of Capital Group or its affiliates. This information is intended to highlight issues and should not be considered advice, an endorsement or a recommendation.\nAll Capital Group trademarks mentioned are owned by The Capital Group Companies, Inc., an affiliated company or fund. All other company and product names mentioned are the property of their respective companies.\nUse of this website is intended for U.S. residents only. Use of this website and materials is also subject to approval by your home office.\nAmerican Funds Distributors, Inc.\nThis content, developed by Capital Group, home of American Funds, should not be used as a primary basis for investment decisions and is not intended to serve as impartial investment or fiduciary advice.",
  "char_count": 8432,
  "audience_track": "advisor",
  "wayback_year": "2023",
  "wayback_snapshot_url": "https://web.archive.org/web/20230924080050/https://www.capitalgroup.com/advisor/insights/articles/why-next-economic-recovery-may-be-stronger-than-expected.html"
}